microprocessor_code/simplest2/Ram_1.v
module ram_1bit_6bit_addr (
    input [5:0] address, 
    input datain,        
    input clear,         
    input store,
    input clk,         
    output dataout       
);

    reg memory [0:63];   
    assign dataout = (clear) ? 1'b0 : memory[address]; 
    integer i;
    initial begin
        memory[0] = 1'b1; 
        memory[1] = 1'b0; 
        memory[2] = 1'b0;
        memory[3] = 1'b0;
        memory[4] = 1'b0;
        memory[5] = 1'b0;

    end


   always @(posedge clk or posedge clear) begin
        if (clear) begin
            for (i = 0; i < 64; i = i + 1) begin
                memory[i] <= 1'b0; 
            end
        end else if (store) begin
            memory[address] <= datain;
        end
        $display("At time %0t, data =  %h, %h, %h, %h, %h, %h", $time, memory[0],memory[1],memory[2],memory[3],memory[4],memory[5]);
    end

endmodule

microprocessor_code/simplest2/Ram_8.v
module ram_8bit_16bit_addr (
    input [15:0] address, 
    input clear,          
    output [7:0] dataout  
);

    reg [7:0] memory [0:65535];  
    integer i;

    initial begin
        memory[0] = 8'h00; 
        memory[1] = 8'h01; 
        memory[2] = 8'h82; 
        memory[3] = 8'h01; 
        memory[4] = 8'h02; 
        memory[5] = 8'h83; 
        memory[6] = 8'h02; 
        memory[7] = 8'h03; 
        memory[8] = 8'h84; 
        memory[9] = 8'h03; 
        memory[10] = 8'h04; 
        memory[11] = 8'h85; 
        // memory[0] = 8'h00; 
        // memory[1] = 8'h01; 
        // memory[2] = 8'h82; 
        // memory[3] = 8'h44; 
        // memory[4] = 8'h02;
        // memory[5] = 8'h02;
        // memory[6] = 8'h82;
        // memory[7] = 8'hFF;
        // memory[10] = 8'h00; 
        // memory[11] = 8'h02; 
        // memory[12] = 8'h80; 
        // memory[13] = 8'h01; 
        // memory[14] = 8'h02; 
        // memory[15] = 8'h81; 
        // memory[16] = 8'hC0; 
 
    end

    assign dataout = (clear) ? 8'b00000000 : memory[address]; 

    always @* begin
        if (clear) begin
            for (i = 0; i < 65536; i = i + 1) begin
                memory[i] = 8'b00000000;  
            end
        end
    end



endmodule

microprocessor_code/Counter.v
module counter_4bit(
    input clk, 
    input reset,
    output [15:0] count
);

    reg [15:0] count_reg;

    always @(posedge clk or posedge reset) begin
        if (reset) 
            count_reg <= 16'b0000000000000000;
        else
            count_reg <= count_reg + 1;
    end

    assign count = count_reg;

endmodule

microprocessor_code/simplest2/Mux2to1.v
module mux_2to1 (
    input A, B, Sel,
    output Y
);

    assign Y = (Sel & B) | (~Sel & A);

endmodule

microprocessor_code/simplest2/Dflipflop.v
module d_flipflop (
    input datain,  
    input clk,    
    input preset, 
    output q 
);

    reg q_reg;

    always @(posedge clk or posedge preset) begin
        if (preset)
            q_reg <= 1'b1;      
        else
            q_reg <= datain;    
    end

    assign q = q_reg;

endmodule

microprocessor_code/simplest2/simplest2.v
`timescale 1ns/1ps

module simplest2(
    input clk,
    input preset,
    input counter_ram8_reset,
    output accumulator_output
);
    
    wire d, p_out, nand_out, mux_out;
    wire [15:0] count_out;
    wire [7:0] ram8_out;
    reg preset_flipflop_input;
    reg accumulator_flipflop_preset;
    reg ram8_clear;
    reg ram1_clear;
    initial begin
        preset_flipflop_input = 1'b0;
        accumulator_flipflop_preset = 1'b0;
        ram8_clear = 1'b0;
        ram1_clear = 1'b0;
    end
    d_flipflop preset_flipflop (
        .datain(preset_flipflop_input),
        .clk(clk),
        .preset((ram8_out[7] | preset)),
        .q(p_out)
    );
    d_flipflop accumulator_flipflop (
        .datain(mux_out),
        .clk(clk),
        .preset(accumulator_flipflop_preset),
        .q(accumulator_output)
    );
    mux_2to1 mux (
        .A(~(d & accumulator_output)),
        .B(d),
        .Sel(p_out),
        .Y(mux_out)
    );
    counter_4bit counter_ram8 (
        .clk(clk),
        .reset(counter_ram8_reset),
        .count(count_out)
    );
    ram_8bit_16bit_addr ram8 (
        .address(count_out),
        .clear(ram8_clear),
        .dataout(ram8_out)
    );
    ram_1bit_6bit_addr ram1 (
        .address({ram8_out[5],ram8_out[4],ram8_out[3],ram8_out[2],ram8_out[1],ram8_out[0]}),
        .datain(accumulator_output),
        .clear(ram1_clear),
        .store(ram8_out[7]),
        .clk(clk),
        .dataout(d)
    );

endmodule

microprocessor_code/simplest2/test.v
// module tb_mux_2to1;
//     reg A, B, Sel;         // Declare inputs as reg
//     wire Y;           

//     mux_2to1 uut (
//         .A(A),
//         .B(B),
//         .Sel(Sel),
//         .Y(Y)
//     );
//     integer i; 

//     initial begin
//         $monitor("Time=%0t A=%b B=%b Sel=%b Y=%b", $time, A, B, Sel, Y);
//         for (i = 0; i < 8; i = i + 1) begin
//             {A, B, Sel} = i;  // Assign i(3 bit number) to A, B, and Sel
//             #10;              // Wait for 10 time units
//         end
//         $finish;
//     end
// endmodule

// `timescale 1ns / 1ps

// module d_flipflop_tb;
//     reg datain;
//     reg clk;
//     reg preset;
//     wire q;

//     d_flipflop uut (
//         .datain(datain),
//         .clk(clk),
//         .preset(preset),
//         .q(q)
//     );

//     always #5 clk = ~clk;

//     initial begin
//         $dumpfile("d_flipflop.vcd");  
//         $dumpvars(0, d_flipflop_tb); //look at all variables

//         clk = 0;
//         datain = 0;
//         preset = 0;

//         #10 preset = 1; 
//         #10 preset = 0; 
        
//         #10 datain = 1;  
//         #10;             
//         #10 datain = 0;  
//         #10;             

//         #20 $finish;
//     end
// endmodule

// module counter_4bit_tb;

//     reg clk;  
//     reg reset;
//     wire [15:0] count; 

//     counter_4bit uut (
//         .clk(clk),
//         .reset(reset),
//         .count(count)
//     );

//     always #5 clk = ~clk;

//     initial begin
//         clk = 0;
//         reset = 0;

//         $monitor("Time: %0t, count: %d, reset: %b", $time, count, reset);

//         #5 reset = 1;  
//         #10 reset = 0; 

//         #50; 

//         #10 reset = 1;   
//         #10 reset = 0;   

//         #50;

//         #10 $finish;
//     end

// endmodule

// `timescale 1ns/1ps

// module ram_8bit_16bit_addr_tb;

//     reg [15:0] address;
//     reg clear;
//     wire [7:0] dataout;

//     ram_8bit_16bit_addr uut (
//         .address(address),
//         .clear(clear),
//         .dataout(dataout)
//     );

//     initial begin
//         $dumpfile("ram_8bit_16bit_addr.vcd");
//         $dumpvars(0, ram_8bit_16bit_addr_tb);

//         clear = 0;
//         address = 16'h0000;

//         #10 address = 16'h0001;
//         #10 address = 16'h0002;

//         #10 clear = 1;   
//         #10 clear = 0;   
//         #10 address = 16'h0001;
//         #10 address = 16'h0002;

//         #10 address = 16'hFFFF;

//         #50 $finish;
//     end

// endmodule

// `timescale 1ns/1ps

// module ram_1bit_6bit_addr_tb;

//     reg [5:0] address;
//     reg datain;
//     reg clear;
//     reg clk;
//     reg store;

//     wire dataout;

//     ram_1bit_6bit_addr uut (
//         .address(address),
//         .datain(datain),
//         .clear(clear),
//         .clk(clk),
//         .store(store),
//         .dataout(dataout)
//     );

//     always #5 clk = ~clk;

//     initial begin
//         $dumpfile("ram_1bit_6bit_addr.vcd");
//         $dumpvars(0, ram_1bit_6bit_addr_tb);

//         clk = 0;
//         clear = 0;
//         store = 0;
//         address = 6'b000000;
//         datain = 0;

//         #10 clear = 1;     
//         #10 clear = 0;     
//         #10 store = 1; datain = 1; address = 6'b000001;
//         #10 store = 1; datain = 0; address = 6'b000010;
//         #10 store = 0; address = 6'b000001;            
//         #10 address = 6'b000010;                       
//         #10 address = 6'b000000;

//         #20 $finish;
//     end

// endmodule


// `timescale 1ns/1ps

// module simplest_tb;

//     reg d;
//     reg clk;
//     reg preset;

//     wire accumulator_output;

//     simplest uut (
//         .d(d),
//         .clk(clk),
//         .preset(preset),
//         .accumulator_output(accumulator_output)
//     );

//     always #5 clk = ~clk;

//     initial begin
//         $dumpfile("main.vcd");
//         $dumpvars(0, main_tb);

//         d=1;
//         clk=0;
//         preset=0;
//         #2
//         preset=1;
//         #1 
//         preset=0;
//         #7
//         d=0;
//         #10
//         d=1;
//         #10
//         d=1;
//         #10
//         d=0;
//         #10
//         d=1;
//         #10
//         d=1;
//         #10
//         d=1;
//         #10
//         d=0;
//         #10
//         d=0;
//         #10
//         d=1;
//         #10
//         d=0;
//         #10
//         preset=1;
//         d=0;
//         #10
//         d=1;
//         preset=0;
//         #10
//         d=0;
//         #10
//         d=1;
//         #10
//         d=1;
//         #20 $finish;
//     end

// endmodule

// `timescale 1ns/1ps

// module simplest2_tb;

//     reg clk;
//     reg preset;
//     reg counter_ram8_reset;

//     wire accumulator_output;

//     simplest2 uut (
//         .clk(clk),
//         .preset(preset),
//         .counter_ram8_reset(counter_ram8_reset),
//         .accumulator_output(accumulator_output)
//     );

//     always #5 clk = ~clk;

//     initial begin
//         $dumpfile("simplest2.vcd");
//         $dumpvars(0, simplest2_tb);

//         clk=0;
//         preset=0;
//         counter_ram8_reset=0;
//         #1
//         preset=1;
//         counter_ram8_reset=1;
//         #2
//         preset=0;
//         counter_ram8_reset=0;
//         #2
//         #120
//         $finish;

//     end

// endmodule

// module stack_tb;

//     reg [15:0] datain;
//     reg clk;
//     reg push, pop;
//     wire [15:0] dataout;

//     stack uut (
//         .datain(datain),
//         .clk(clk),
//         .push(push),
//         .pop(pop),
//         .dataout(dataout)
//     );
//     always #5 clk = ~clk;

//     initial begin
//         clk = 0;
//     end

//     initial begin
//         $dumpfile("stack.vcd");
//         $dumpvars(0, stack_tb);

//         datain = 0;
//         push = 0;
//         pop = 0;

//         #10 datain = 16'hAAAA; push = 1; #10 push = 0;
//         #10 datain = 16'hBBBB; push = 1; #10 push = 0;
//         #10 datain = 16'hCCCC; push = 1; #10 push = 0;

//         #10 pop = 1; #10 pop = 0;
//         #10 pop = 1; #10 pop = 0;
//         #10 pop = 1; #10 pop = 0;


//         $finish;
//     end
// endmodule

// module counter_16bit_tb;

//     reg clk;
//     reg reset;
//     reg load;
//     reg [15:0] datain;
//     wire [15:0] dataout;

//     counter_16bit uut (
//         .clk(clk),
//         .reset(reset),
//         .datain(datain),
//         .load(load),
//         .dataout(dataout)
//     );

//     always #5 clk = ~clk;

//     initial begin
//         $dumpfile("counter_better.vcd");
//         $dumpvars(0, counter_16bit_tb);


//         clk = 0;
//         reset = 0;
//         load = 0;
//         datain = 16'b0000000000000000;

//         #10 reset = 1;
//         #10 reset = 0;

//         #10 load = 1; datain = 16'h1234;
//         #10 load = 0;                   

//         #50;                            

//         #10 load = 1; datain = 16'h1567;
//         #10 load = 0;                   

//         #50;                            


//         #10 reset = 1;                  
//         #10 reset = 0;

//         #50 $finish;                    
//     end

// endmodule

// `timescale 1ns/1ps

// module simplest3_tb;

//     reg clk;
//     reg preset;
//     reg counter_ram8_reset;

//     wire accumulator_output;

//     simplest3 uut (
//         .clk(clk),
//         .preset(preset),
//         .counter_ram8_reset(counter_ram8_reset),
//         .accumulator_output(accumulator_output)
//     );

//     always #5 clk = ~clk;

//     initial begin
//         $dumpfile("simplest3.vcd");
//         $dumpvars(0, simplest3_tb);

//         clk=0;
//         preset=0;
//         counter_ram8_reset=0;
//         #1
//         preset=1;
//         counter_ram8_reset=1;
//         #2
//         preset=0;
//         counter_ram8_reset=0;
//         #2
//         #800
//         $finish;

//     end

// endmodule

// `timescale 1ns/1ps

// module simplest4_para_tb;

//     reg clk;
//     reg preset;
//     reg counter_ram8_reset;

//     wire accumulator_output0;
//     wire accumulator_output1;
//     wire accumulator_output2;
//     wire accumulator_output3;

//     simplest4_para uut (
//         .clk(clk),
//         .preset(preset),
//         .counter_ram8_reset(counter_ram8_reset),
//         .accumulator_output0(accumulator_output0),
//         .accumulator_output1(accumulator_output1),
//         .accumulator_output2(accumulator_output2),
//         .accumulator_output3(accumulator_output3)

//     );

//     always #5 clk = ~clk;

//     initial begin
//         $dumpfile("simplest4_para.vcd");
//         $dumpvars(0, simplest4_para_tb);

//         clk=0;
//         preset=0;
//         #1
//         preset=1;
//         #2
//         preset=0;
//         #2
//         #5
//         $finish;

//     end

// endmodule

// `timescale 1ns/1ps

// module simplest_tb;

//     reg d;
//     reg clk;
//     reg preset;

//     wire accumulator_output;

//     simplest uut (
//         .d(d),
//         .clk(clk),
//         .preset(preset),
//         .accumulator_output(accumulator_output)
//     );

//     always #5 clk = ~clk;

//     initial begin
//         $dumpfile("simplest.vcd");
//         $dumpvars(0, simplest_tb);

//         d=1;
//         clk=0;
//         preset=0;
//         #2
//         preset=1;
//         #1 
//         preset=0;
//         #7
//         d=0;
//         #10
//         d=1;
//         #10
//         d=1;
//         #10
//         d=0;
//         #10
//         d=1;
//         #10
//         d=1;
//         #10
//         d=1;
//         #10
//         d=0;
//         #10
//         d=0;
//         #10
//         d=1;
//         #10
//         d=0;
//         #10
//         preset=1;
//         d=0;
//         #10
//         d=1;
//         preset=0;
//         #10
//         d=0;
//         #10
//         d=1;
//         #10
//         d=1;
//         #20 $finish;
//     end

// endmodule

`timescale 1ns/1ps

module simplest2_tb;

    reg clk;
    reg preset;
    reg counter_ram8_reset;

    wire accumulator_output;

    simplest2 uut (
        .clk(clk),
        .preset(preset),
        .counter_ram8_reset(counter_ram8_reset),
        .accumulator_output(accumulator_output)
    );

    always #5 clk = ~clk;

    initial begin
        $dumpfile("simplest2.vcd");
        $dumpvars(0, simplest2_tb);

        clk=0;
        preset=0;
        counter_ram8_reset=0;
        #1
        preset=1;
        counter_ram8_reset=1;
        #2
        preset=0;
        counter_ram8_reset=0;
        #2
        #120
        
        $finish;

    end

endmodule

microprocessor_code/simplest2/simplest2.vcd
$date
	Wed Jan 22 22:09:22 2025
$end
$version
	Icarus Verilog
$end
$timescale
	1ps
$end
$scope module simplest2_tb $end
$var wire 1 ! accumulator_output $end
$var reg 1 " clk $end
$var reg 1 # counter_ram8_reset $end
$var reg 1 $ preset $end
$scope module uut $end
$var wire 1 " clk $end
$var wire 1 # counter_ram8_reset $end
$var wire 1 $ preset $end
$var wire 8 % ram8_out [7:0] $end
$var wire 1 & p_out $end
$var wire 1 ' mux_out $end
$var wire 1 ( d $end
$var wire 16 ) count_out [15:0] $end
$var wire 1 ! accumulator_output $end
$var reg 1 * accumulator_flipflop_preset $end
$var reg 1 + preset_flipflop_input $end
$var reg 1 , ram1_clear $end
$var reg 1 - ram8_clear $end
$scope module accumulator_flipflop $end
$var wire 1 " clk $end
$var wire 1 * preset $end
$var wire 1 ! q $end
$var wire 1 ' datain $end
$var reg 1 ! q_reg $end
$upscope $end
$scope module counter_ram8 $end
$var wire 1 " clk $end
$var wire 1 # reset $end
$var wire 16 . count [15:0] $end
$var reg 16 / count_reg [15:0] $end
$upscope $end
$scope module mux $end
$var wire 1 0 A $end
$var wire 1 ' Y $end
$var wire 1 & Sel $end
$var wire 1 ( B $end
$upscope $end
$scope module preset_flipflop $end
$var wire 1 " clk $end
$var wire 1 + datain $end
$var wire 1 1 preset $end
$var wire 1 & q $end
$var reg 1 & q_reg $end
$upscope $end
$scope module ram1 $end
$var wire 6 2 address [5:0] $end
$var wire 1 , clear $end
$var wire 1 " clk $end
$var wire 1 ! datain $end
$var wire 1 3 store $end
$var wire 1 ( dataout $end
$var integer 32 4 i [31:0] $end
$upscope $end
$scope module ram8 $end
$var wire 16 5 address [15:0] $end
$var wire 1 - clear $end
$var wire 8 6 dataout [7:0] $end
$var integer 32 7 i [31:0] $end
$upscope $end
$upscope $end
$upscope $end
$enddefinitions $end
$comment Show the parameter values. $end
$dumpall
$end
#0
$dumpvars
bx 7
bx 6
bx 5
bx 4
x3
bx 2
x1
x0
bx /
bx .
0-
0,
0+
0*
bx )
x(
x'
x&
bx %
0$
0#
0"
x!
$end
#1000
1'
1(
03
b0 2
b0 %
b0 6
1&
b0 )
b0 .
b0 /
b0 5
11
1#
1$
#3000
01
0#
0$
#5000
0(
10
b1 2
1'
b1 %
b1 6
1!
b1 )
b1 .
b1 /
b1 5
0&
1"
#10000
0"
#15000
0'
1&
11
13
b10 2
b10000010 %
b10000010 6
b10 )
b10 .
b10 /
b10 5
1"
#20000
0"
#25000
01
0'
03
b1 2
b1 %
b1 6
0(
0!
b11 )
b11 .
b11 /
b11 5
1"
#30000
0"
#35000
1(
1'
b10 2
b10 %
b10 6
b100 )
b100 .
b100 /
b100 5
0&
1"
#40000
0"
#45000
1&
0'
0(
11
10
13
b11 2
b10000011 %
b10000011 6
1!
b101 )
b101 .
b101 /
b101 5
1"
#50000
0"
#55000
01
1'
03
b10 2
b10 %
b10 6
1(
0!
b110 )
b110 .
b110 /
b110 5
1"
#60000
0"
#65000
00
b11 2
0'
b11 %
b11 6
1!
b111 )
b111 .
b111 /
b111 5
0&
1"
#70000
0"
#75000
1&
0'
0(
11
10
13
b100 2
b10000100 %
b10000100 6
0!
b1000 )
b1000 .
b1000 /
b1000 5
1"
#80000
0"
#85000
1'
1(
01
03
b11 2
b11 %
b11 6
b1001 )
b1001 .
b1001 /
b1001 5
1"
#90000
0"
#95000
0(
10
b100 2
1'
b100 %
b100 6
1!
b1010 )
b1010 .
b1010 /
b1010 5
0&
1"
#100000
0"
#105000
0'
1&
11
13
b101 2
b10000101 %
b10000101 6
b1011 )
b1011 .
b1011 /
b1011 5
1"
#110000
0"
#115000
x1
x'
x3
bx 2
bx %
bx 6
x(
0!
b1100 )
b1100 .
b1100 /
b1100 5
1"
#120000
0"
#125000
x0
x'
x!
b1101 )
b1101 .
b1101 /
b1101 5
0&
1"
